django_unsaved_changes/__init__.py
django_unsaved_changes/admin.py
django_unsaved_changes/static/unsaved_changes/css/unsaved_changes.css
django_unsaved_changes/static/unsaved_changes/js/unsaved_changes.jqueryplugin.js
django_unsaved_changes/static/unsaved_changes/js/vendor/garlic.js
django_unsaved_changes/static/unsaved_changes/js/vendor/jquery.js
django_unsaved_changes/templates/admin/django_unsaved_changes/change_form.html
django_unsaved_changes/templatetags/__init__.py
django_unsaved_changes/templatetags/unsaved_changes_tags.py
django_unsaved_changes-1.1.0.dist-info/DESCRIPTION.rst
django_unsaved_changes-1.1.0.dist-info/METADATA
django_unsaved_changes-1.1.0.dist-info/RECORD
django_unsaved_changes-1.1.0.dist-info/WHEEL
django_unsaved_changes-1.1.0.dist-info/metadata.json
django_unsaved_changes-1.1.0.dist-info/top_level.txt
