Metadata-Version: 2.0
Name: django-unsaved-changes
Version: 1.1.0
Summary: UX improvements for admin
Home-page: https://github.com/ninapavlich/django-unsaved-changes
Author: Nina Pavlich
Author-email: nina@ninalp.com
License: MIT
Keywords: libraries,web development
Platform: UNKNOWN
Classifier: Development Status :: 4 - Beta
Classifier: Environment :: Web Environment
Classifier: Framework :: Django
Classifier: Intended Audience :: Developers
Classifier: License :: OSI Approved :: MIT License
Classifier: Natural Language :: English
Classifier: Operating System :: OS Independent
Classifier: Programming Language :: Python
